crowdom/__init__.py
crowdom/__version__.py
crowdom/duration.py
crowdom/pool.py
crowdom/pricing.py
crowdom/task_spec.py
crowdom/utils.py
crowdom/base/__init__.py
crowdom/base/common.py
crowdom/base/conditions.py
crowdom/base/functions.py
crowdom/base/metas.py
crowdom/base/task.py
crowdom/base/types.py
crowdom/bots/__init__.py
crowdom/bots/client.py
crowdom/bots/util.py
crowdom/bots/worker.py
crowdom/classification/__init__.py
crowdom/classification_loop/__init__.py
crowdom/client/__init__.py
crowdom/client/display.py
crowdom/client/launch.py
crowdom/client/task.py
crowdom/client/training.py
crowdom/client/utils.py
crowdom/contrib/__init__.py
crowdom/contrib/lzstring.py
crowdom/control/__init__.py
crowdom/control/rule.py
crowdom/control/rule_builder.py
crowdom/datasource/__init__.py
crowdom/datasource/media.py
crowdom/datasource/tasks.py
crowdom/evaluation/__init__.py
crowdom/experts/__init__.py
crowdom/experts/base.py
crowdom/experts/lzy.py
crowdom/experts/pipeline.py
crowdom/experts/registration.py
crowdom/experts/training.py
crowdom/feedback_loop/__init__.py
crowdom/feedback_loop/metrics.py
crowdom/feedback_loop/params.py
crowdom/feedback_loop/pipeline.py
crowdom/feedback_loop/results.py
crowdom/instruction/__init__.py
crowdom/instruction/acceptance.py
crowdom/instruction/annotation_check.py
crowdom/instruction/css.py
crowdom/instruction/experts.py
crowdom/lzy/__init__.py
crowdom/lzy/serialization/__init__.py
crowdom/lzy/serialization/annotation.py
crowdom/lzy/serialization/base.py
crowdom/lzy/serialization/classification.py
crowdom/lzy/serialization/classification_loop.py
crowdom/lzy/serialization/client.py
crowdom/lzy/serialization/common.py
crowdom/lzy/serialization/control.py
crowdom/lzy/serialization/evaluation.py
crowdom/lzy/serialization/mapping.py
crowdom/lzy/serialization/pricing.py
crowdom/lzy/serialization/toloka.py
crowdom/lzy/serialization/worker.py
crowdom/lzy/workflows/__init__.py
crowdom/lzy/workflows/annotation.py
crowdom-0.2.0.dist-info/AUTHORS
crowdom-0.2.0.dist-info/LICENSE
crowdom-0.2.0.dist-info/METADATA
crowdom-0.2.0.dist-info/WHEEL
crowdom-0.2.0.dist-info/top_level.txt
crowdom-0.2.0.dist-info/RECORD
