Metadata-Version: 2.1
Name: crowdom
Version: 0.2.0
Summary: Crowdom
Author: Oleg Gulyaev
Author-email: o-gulyaev@yandex-team.ru
License: Apache 2.0
Requires-Python: >=3.8.0
License-File: LICENSE
License-File: AUTHORS
